odoo/addons/l10n_br_sale/README.rst
odoo/addons/l10n_br_sale/__init__.py
odoo/addons/l10n_br_sale/__manifest__.py
odoo/addons/l10n_br_sale/hooks.py
odoo/addons/l10n_br_sale/data/company.xml
odoo/addons/l10n_br_sale/demo/company.xml
odoo/addons/l10n_br_sale/demo/l10n_br_sale.xml
odoo/addons/l10n_br_sale/demo/product.xml
odoo/addons/l10n_br_sale/i18n/l10n_br_sale.pot
odoo/addons/l10n_br_sale/i18n/pt_BR.po
odoo/addons/l10n_br_sale/migrations/16.0.6.0.0/pre-migration.py
odoo/addons/l10n_br_sale/models/__init__.py
odoo/addons/l10n_br_sale/models/res_company.py
odoo/addons/l10n_br_sale/models/res_config_settings.py
odoo/addons/l10n_br_sale/models/sale_order.py
odoo/addons/l10n_br_sale/models/sale_order_line.py
odoo/addons/l10n_br_sale/readme/CONFIGURE.md
odoo/addons/l10n_br_sale/readme/CONTRIBUTORS.md
odoo/addons/l10n_br_sale/readme/CREDITS.md
odoo/addons/l10n_br_sale/readme/DESCRIPTION.md
odoo/addons/l10n_br_sale/readme/HISTORY.md
odoo/addons/l10n_br_sale/readme/INSTALL.md
odoo/addons/l10n_br_sale/readme/ROADMAP.md
odoo/addons/l10n_br_sale/readme/USAGE.md
odoo/addons/l10n_br_sale/report/__init__.py
odoo/addons/l10n_br_sale/report/sale_report.py
odoo/addons/l10n_br_sale/report/sale_report_templates.xml
odoo/addons/l10n_br_sale/report/sale_report_view.xml
odoo/addons/l10n_br_sale/security/ir.model.access.csv
odoo/addons/l10n_br_sale/security/l10n_br_sale_security.xml
odoo/addons/l10n_br_sale/static/description/icon.png
odoo/addons/l10n_br_sale/static/description/index.html
odoo/addons/l10n_br_sale/static/description/sale_order_1.png
odoo/addons/l10n_br_sale/static/description/sale_order_2.png
odoo/addons/l10n_br_sale/tests/__init__.py
odoo/addons/l10n_br_sale/tests/test_l10n_br_sale.py
odoo/addons/l10n_br_sale/tests/test_l10n_br_sale_discount.py
odoo/addons/l10n_br_sale/tests/test_l10n_br_sale_lp.py
odoo/addons/l10n_br_sale/tests/test_l10n_br_sale_pricelist.py
odoo/addons/l10n_br_sale/tests/test_l10n_br_sale_sn.py
odoo/addons/l10n_br_sale/tests/test_sale_order_report.py
odoo_addon_l10n_br_sale-16.0.8.0.0.dist-info/METADATA
odoo_addon_l10n_br_sale-16.0.8.0.0.dist-info/WHEEL
odoo_addon_l10n_br_sale-16.0.8.0.0.dist-info/top_level.txt
odoo_addon_l10n_br_sale-16.0.8.0.0.dist-info/RECORD
